{
  "query": "\nSELECT \n  id,\n  section,\n  entity,\n  status,\n  current_stage,\n  progress,\n  resume_page,\n  error_message,\n  started_at,\n  finished_at,\n  TIMESTAMPDIFF(MINUTE, started_at, IFNULL(finished_at, NOW())) AS duration_min\nFROM sync_logs\nORDER BY id DESC\nLIMIT 20;\n",
  "command": "mysql --batch --raw --column-names --default-character-set=utf8mb4 --host gateway05.us-east-1.prod.aws.tidbcloud.com --port 4000 --user 3zL6E4esQEHiYzS.root --database WPSwtnWiTSyEVhTdqqAYk7 --execute \nSELECT \n  id,\n  section,\n  entity,\n  status,\n  current_stage,\n  progress,\n  resume_page,\n  error_message,\n  started_at,\n  finished_at,\n  TIMESTAMPDIFF(MINUTE, started_at, IFNULL(finished_at, NOW())) AS duration_min\nFROM sync_logs\nORDER BY id DESC\nLIMIT 20;\n",
  "rows": [
    {
      "id": "1620027",
      "section": "Boonphone",
      "entity": "payments",
      "status": "success",
      "current_stage": "NULL",
      "progress": "0",
      "resume_page": "0",
      "error_message": "NULL",
      "started_at": "2026-05-14 08:21:36",
      "finished_at": "2026-05-14 08:21:52",
      "duration_min": "0"
    },
    {
      "id": "1620026",
      "section": "Boonphone",
      "entity": "installments",
      "status": "success",
      "current_stage": "NULL",
      "progress": "0",
      "resume_page": "0",
      "error_message": "NULL",
      "started_at": "2026-05-14 08:17:43",
      "finished_at": "2026-05-14 08:21:36",
      "duration_min": "3"
    },
    {
      "id": "1620025",
      "section": "Boonphone",
      "entity": "contracts",
      "status": "success",
      "current_stage": "contracts",
      "progress": "100",
      "resume_page": "23",
      "error_message": "NULL",
      "started_at": "2026-05-14 08:14:27",
      "finished_at": "2026-05-14 08:17:43",
      "duration_min": "3"
    },
    {
      "id": "1620024",
      "section": "Boonphone",
      "entity": "customers",
      "status": "success",
      "current_stage": "NULL",
      "progress": "0",
      "resume_page": "0",
      "error_message": "NULL",
      "started_at": "2026-05-14 08:14:24",
      "finished_at": "2026-05-14 08:14:25",
      "duration_min": "0"
    },
    {
      "id": "1620023",
      "section": "Boonphone",
      "entity": "partners",
      "status": "success",
      "current_stage": "NULL",
      "progress": "0",
      "resume_page": "0",
      "error_message": "NULL",
      "started_at": "2026-05-14 08:14:17",
      "finished_at": "2026-05-14 08:14:24",
      "duration_min": "0"
    },
    {
      "id": "1620022",
      "section": "Boonphone",
      "entity": "all",
      "status": "success",
      "current_stage": "bad_debt",
      "progress": "80",
      "resume_page": "12",
      "error_message": "NULL",
      "started_at": "2026-05-14 08:14:17",
      "finished_at": "2026-05-14 08:22:35",
      "duration_min": "8"
    },
    {
      "id": "1620021",
      "section": "Fastfone365",
      "entity": "partners",
      "status": "error",
      "current_stage": "NULL",
      "progress": "0",
      "resume_page": "0",
      "error_message": "Auto-cleared on startup: previous Cloud Run instance was killed during sync",
      "started_at": "2026-05-14 08:00:16",
      "finished_at": "2026-05-14 08:15:31",
      "duration_min": "15"
    },
    {
      "id": "1620020",
      "section": "Fastfone365",
      "entity": "all",
      "status": "error",
      "current_stage": "partners",
      "progress": "5",
      "resume_page": "0",
      "error_message": "Auto-cleared on startup: previous Cloud Run instance was killed during sync",
      "started_at": "2026-05-14 08:00:16",
      "finished_at": "2026-05-14 08:15:31",
      "duration_min": "15"
    },
    {
      "id": "1620019",
      "section": "Fastfone365",
      "entity": "payments",
      "status": "error",
      "current_stage": "NULL",
      "progress": "0",
      "resume_page": "0",
      "error_message": "Auto-cleared on startup: previous Cloud Run instance was killed during sync",
      "started_at": "2026-05-14 07:54:48",
      "finished_at": "2026-05-14 08:14:15",
      "duration_min": "19"
    },
    {
      "id": "1620018",
      "section": "Boonphone",
      "entity": "contracts",
      "status": "error",
      "current_stage": "contracts",
      "progress": "55",
      "resume_page": "13",
      "error_message": "Auto-cleared on startup: previous Cloud Run instance was killed during sync",
      "started_at": "2026-05-14 07:43:40",
      "finished_at": "2026-05-14 08:00:14",
      "duration_min": "16"
    },
    {
      "id": "1620017",
      "section": "Boonphone",
      "entity": "customers",
      "status": "success",
      "current_stage": "NULL",
      "progress": "0",
      "resume_page": "0",
      "error_message": "NULL",
      "started_at": "2026-05-14 07:43:33",
      "finished_at": "2026-05-14 07:43:40",
      "duration_min": "0"
    },
    {
      "id": "1620016",
      "section": "Boonphone",
      "entity": "partners",
      "status": "success",
      "current_stage": "NULL",
      "progress": "0",
      "resume_page": "0",
      "error_message": "NULL",
      "started_at": "2026-05-14 07:43:28",
      "finished_at": "2026-05-14 07:43:32",
      "duration_min": "0"
    },
    {
      "id": "1620015",
      "section": "Boonphone",
      "entity": "all",
      "status": "error",
      "current_stage": "customers (10/10)",
      "progress": "40",
      "resume_page": "11",
      "error_message": "Auto-cleared on startup: previous Cloud Run instance was killed during sync",
      "started_at": "2026-05-14 07:43:28",
      "finished_at": "2026-05-14 08:00:14",
      "duration_min": "16"
    },
    {
      "id": "1620014",
      "section": "Fastfone365",
      "entity": "installments",
      "status": "success",
      "current_stage": "NULL",
      "progress": "0",
      "resume_page": "0",
      "error_message": "NULL",
      "started_at": "2026-05-14 07:40:37",
      "finished_at": "2026-05-14 07:54:48",
      "duration_min": "14"
    },
    {
      "id": "1620013",
      "section": "Fastfone365",
      "entity": "contracts",
      "status": "success",
      "current_stage": "contracts",
      "progress": "100",
      "resume_page": "91",
      "error_message": "NULL",
      "started_at": "2026-05-14 07:31:12",
      "finished_at": "2026-05-14 07:40:36",
      "duration_min": "9"
    },
    {
      "id": "1620012",
      "section": "Fastfone365",
      "entity": "customers",
      "status": "success",
      "current_stage": "NULL",
      "progress": "0",
      "resume_page": "0",
      "error_message": "NULL",
      "started_at": "2026-05-14 07:28:58",
      "finished_at": "2026-05-14 07:31:10",
      "duration_min": "2"
    },
    {
      "id": "1620011",
      "section": "Fastfone365",
      "entity": "partners",
      "status": "success",
      "current_stage": "NULL",
      "progress": "0",
      "resume_page": "0",
      "error_message": "NULL",
      "started_at": "2026-05-14 07:28:46",
      "finished_at": "2026-05-14 07:28:56",
      "duration_min": "0"
    },
    {
      "id": "1620010",
      "section": "Fastfone365",
      "entity": "all",
      "status": "error",
      "current_stage": "payments",
      "progress": "65",
      "resume_page": "46",
      "error_message": "Auto-cleared on startup: previous Cloud Run instance was killed during sync",
      "started_at": "2026-05-14 07:28:45",
      "finished_at": "2026-05-14 07:44:17",
      "duration_min": "15"
    },
    {
      "id": "1620009",
      "section": "Boonphone",
      "entity": "customers",
      "status": "error",
      "current_stage": "NULL",
      "progress": "0",
      "resume_page": "0",
      "error_message": "Force-cleared by admin: Cloud Run instance killed during sync",
      "started_at": "2026-05-14 07:11:58",
      "finished_at": "2026-05-14 07:24:27",
      "duration_min": "12"
    },
    {
      "id": "1620008",
      "section": "Boonphone",
      "entity": "partners",
      "status": "success",
      "current_stage": "NULL",
      "progress": "0",
      "resume_page": "0",
      "error_message": "NULL",
      "started_at": "2026-05-14 07:11:54",
      "finished_at": "2026-05-14 07:11:58",
      "duration_min": "0"
    }
  ],
  "messages": [],
  "stdout": "id\tsection\tentity\tstatus\tcurrent_stage\tprogress\tresume_page\terror_message\tstarted_at\tfinished_at\tduration_min\n1620027\tBoonphone\tpayments\tsuccess\tNULL\t0\t0\tNULL\t2026-05-14 08:21:36\t2026-05-14 08:21:52\t0\n1620026\tBoonphone\tinstallments\tsuccess\tNULL\t0\t0\tNULL\t2026-05-14 08:17:43\t2026-05-14 08:21:36\t3\n1620025\tBoonphone\tcontracts\tsuccess\tcontracts\t100\t23\tNULL\t2026-05-14 08:14:27\t2026-05-14 08:17:43\t3\n1620024\tBoonphone\tcustomers\tsuccess\tNULL\t0\t0\tNULL\t2026-05-14 08:14:24\t2026-05-14 08:14:25\t0\n1620023\tBoonphone\tpartners\tsuccess\tNULL\t0\t0\tNULL\t2026-05-14 08:14:17\t2026-05-14 08:14:24\t0\n1620022\tBoonphone\tall\tsuccess\tbad_debt\t80\t12\tNULL\t2026-05-14 08:14:17\t2026-05-14 08:22:35\t8\n1620021\tFastfone365\tpartners\terror\tNULL\t0\t0\tAuto-cleared on startup: previous Cloud Run instance was killed during sync\t2026-05-14 08:00:16\t2026-05-14 08:15:31\t15\n1620020\tFastfone365\tall\terror\tpartners\t5\t0\tAuto-cleared on startup: previous Cloud Run instance was killed during sync\t2026-05-14 08:00:16\t2026-05-14 08:15:31\t15\n1620019\tFastfone365\tpayments\terror\tNULL\t0\t0\tAuto-cleared on startup: previous Cloud Run instance was killed during sync\t2026-05-14 07:54:48\t2026-05-14 08:14:15\t19\n1620018\tBoonphone\tcontracts\terror\tcontracts\t55\t13\tAuto-cleared on startup: previous Cloud Run instance was killed during sync\t2026-05-14 07:43:40\t2026-05-14 08:00:14\t16\n1620017\tBoonphone\tcustomers\tsuccess\tNULL\t0\t0\tNULL\t2026-05-14 07:43:33\t2026-05-14 07:43:40\t0\n1620016\tBoonphone\tpartners\tsuccess\tNULL\t0\t0\tNULL\t2026-05-14 07:43:28\t2026-05-14 07:43:32\t0\n1620015\tBoonphone\tall\terror\tcustomers (10/10)\t40\t11\tAuto-cleared on startup: previous Cloud Run instance was killed during sync\t2026-05-14 07:43:28\t2026-05-14 08:00:14\t16\n1620014\tFastfone365\tinstallments\tsuccess\tNULL\t0\t0\tNULL\t2026-05-14 07:40:37\t2026-05-14 07:54:48\t14\n1620013\tFastfone365\tcontracts\tsuccess\tcontracts\t100\t91\tNULL\t2026-05-14 07:31:12\t2026-05-14 07:40:36\t9\n1620012\tFastfone365\tcustomers\tsuccess\tNULL\t0\t0\tNULL\t2026-05-14 07:28:58\t2026-05-14 07:31:10\t2\n1620011\tFastfone365\tpartners\tsuccess\tNULL\t0\t0\tNULL\t2026-05-14 07:28:46\t2026-05-14 07:28:56\t0\n1620010\tFastfone365\tall\terror\tpayments\t65\t46\tAuto-cleared on startup: previous Cloud Run instance was killed during sync\t2026-05-14 07:28:45\t2026-05-14 07:44:17\t15\n1620009\tBoonphone\tcustomers\terror\tNULL\t0\t0\tForce-cleared by admin: Cloud Run instance killed during sync\t2026-05-14 07:11:58\t2026-05-14 07:24:27\t12\n1620008\tBoonphone\tpartners\tsuccess\tNULL\t0\t0\tNULL\t2026-05-14 07:11:54\t2026-05-14 07:11:58\t0\n",
  "stderr": "",
  "execution_time_ms": 1846
}