{
  "query": "\nSELECT\n  DATE(paid_at) AS paid_date,\n  SUM(CAST(amount AS DECIMAL(18,2))) AS sum_amount,\n  COUNT(*) AS tx_count,\n  SUM(CAST(JSON_EXTRACT(raw_json, '$.principal_paid') AS DECIMAL(18,2))) AS sum_principal,\n  SUM(CAST(JSON_EXTRACT(raw_json, '$.interest_paid') AS DECIMAL(18,2))) AS sum_interest,\n  SUM(CAST(JSON_EXTRACT(raw_json, '$.fee_paid') AS DECIMAL(18,2))) AS sum_fee,\n  SUM(CAST(JSON_EXTRACT(raw_json, '$.penalty_paid') AS DECIMAL(18,2))) AS sum_penalty,\n  SUM(CAST(JSON_EXTRACT(raw_json, '$.overpaid_amount') AS DECIMAL(18,2))) AS sum_overpaid,\n  SUM(CAST(JSON_EXTRACT(raw_json, '$.close_installment_amount') AS DECIMAL(18,2))) AS sum_close,\n  SUM(CAST(JSON_EXTRACT(raw_json, '$.bad_debt_amount') AS DECIMAL(18,2))) AS sum_bad_debt\nFROM payment_transactions\nWHERE section = 'Fastfone365'\n  AND DATE(paid_at) BETWEEN '2026-04-01' AND '2026-04-30'\nGROUP BY DATE(paid_at)\nORDER BY paid_date ASC;\n",
  "command": "mysql --batch --raw --column-names --default-character-set=utf8mb4 --host gateway05.us-east-1.prod.aws.tidbcloud.com --port 4000 --user 3zL6E4esQEHiYzS.root --database WPSwtnWiTSyEVhTdqqAYk7 --execute \nSELECT\n  DATE(paid_at) AS paid_date,\n  SUM(CAST(amount AS DECIMAL(18,2))) AS sum_amount,\n  COUNT(*) AS tx_count,\n  SUM(CAST(JSON_EXTRACT(raw_json, '$.principal_paid') AS DECIMAL(18,2))) AS sum_principal,\n  SUM(CAST(JSON_EXTRACT(raw_json, '$.interest_paid') AS DECIMAL(18,2))) AS sum_interest,\n  SUM(CAST(JSON_EXTRACT(raw_json, '$.fee_paid') AS DECIMAL(18,2))) AS sum_fee,\n  SUM(CAST(JSON_EXTRACT(raw_json, '$.penalty_paid') AS DECIMAL(18,2))) AS sum_penalty,\n  SUM(CAST(JSON_EXTRACT(raw_json, '$.overpaid_amount') AS DECIMAL(18,2))) AS sum_overpaid,\n  SUM(CAST(JSON_EXTRACT(raw_json, '$.close_installment_amount') AS DECIMAL(18,2))) AS sum_close,\n  SUM(CAST(JSON_EXTRACT(raw_json, '$.bad_debt_amount') AS DECIMAL(18,2))) AS sum_bad_debt\nFROM payment_transactions\nWHERE section = 'Fastfone365'\n  AND DATE(paid_at) BETWEEN '2026-04-01' AND '2026-04-30'\nGROUP BY DATE(paid_at)\nORDER BY paid_date ASC;\n",
  "rows": [
    {
      "paid_date": "2026-04-01",
      "sum_amount": "1667588.78",
      "tx_count": "636",
      "sum_principal": "346120.95",
      "sum_interest": "413689.94",
      "sum_fee": "28085.00",
      "sum_penalty": "13540.00",
      "sum_overpaid": "1270.00",
      "sum_close": "787212.89",
      "sum_bad_debt": "0.00"
    },
    {
      "paid_date": "2026-04-02",
      "sum_amount": "1146813.63",
      "tx_count": "455",
      "sum_principal": "210872.08",
      "sum_interest": "264002.55",
      "sum_fee": "17383.00",
      "sum_penalty": "4589.00",
      "sum_overpaid": "12816.00",
      "sum_close": "492257.63",
      "sum_bad_debt": "0.00"
    },
    {
      "paid_date": "2026-04-03",
      "sum_amount": "1249910.60",
      "tx_count": "411",
      "sum_principal": "253146.75",
      "sum_interest": "303189.01",
      "sum_fee": "19092.00",
      "sum_penalty": "7019.00",
      "sum_overpaid": "164061.24",
      "sum_close": "575011.56",
      "sum_bad_debt": "0.00"
    },
    {
      "paid_date": "2026-04-04",
      "sum_amount": "844897.00",
      "tx_count": "331",
      "sum_principal": "175633.25",
      "sum_interest": "223059.75",
      "sum_fee": "14103.00",
      "sum_penalty": "6372.00",
      "sum_overpaid": "1395.00",
      "sum_close": "412796.00",
      "sum_bad_debt": "0.00"
    },
    {
      "paid_date": "2026-04-05",
      "sum_amount": "1661913.00",
      "tx_count": "625",
      "sum_principal": "360284.00",
      "sum_interest": "445775.00",
      "sum_fee": "29741.00",
      "sum_penalty": "10415.00",
      "sum_overpaid": "8715.00",
      "sum_close": "835800.00",
      "sum_bad_debt": "0.00"
    },
    {
      "paid_date": "2026-04-06",
      "sum_amount": "1321682.65",
      "tx_count": "419",
      "sum_principal": "195670.00",
      "sum_interest": "242089.84",
      "sum_fee": "15443.00",
      "sum_penalty": "6150.00",
      "sum_overpaid": "210574.16",
      "sum_close": "446141.84",
      "sum_bad_debt": "0.00"
    },
    {
      "paid_date": "2026-04-07",
      "sum_amount": "741852.10",
      "tx_count": "310",
      "sum_principal": "147170.00",
      "sum_interest": "198090.00",
      "sum_fee": "12223.00",
      "sum_penalty": "4450.50",
      "sum_overpaid": "0.00",
      "sum_close": "355632.80",
      "sum_bad_debt": "0.00"
    },
    {
      "paid_date": "2026-04-08",
      "sum_amount": "957966.00",
      "tx_count": "340",
      "sum_principal": "189267.00",
      "sum_interest": "251951.00",
      "sum_fee": "15163.00",
      "sum_penalty": "6532.00",
      "sum_overpaid": "68129.00",
      "sum_close": "456381.00",
      "sum_bad_debt": "0.00"
    },
    {
      "paid_date": "2026-04-09",
      "sum_amount": "805934.34",
      "tx_count": "321",
      "sum_principal": "175563.25",
      "sum_interest": "237727.05",
      "sum_fee": "14418.00",
      "sum_penalty": "8957.00",
      "sum_overpaid": "2426.58",
      "sum_close": "427708.30",
      "sum_bad_debt": "0.00"
    },
    {
      "paid_date": "2026-04-10",
      "sum_amount": "2250142.83",
      "tx_count": "851",
      "sum_principal": "489209.58",
      "sum_interest": "598746.91",
      "sum_fee": "38016.00",
      "sum_penalty": "15852.88",
      "sum_overpaid": "4305.63",
      "sum_close": "1124515.09",
      "sum_bad_debt": "0.00"
    },
    {
      "paid_date": "2026-04-11",
      "sum_amount": "823933.04",
      "tx_count": "307",
      "sum_principal": "153413.00",
      "sum_interest": "194742.00",
      "sum_fee": "12397.00",
      "sum_penalty": "4262.00",
      "sum_overpaid": "2333.00",
      "sum_close": "360552.00",
      "sum_bad_debt": "0.00"
    },
    {
      "paid_date": "2026-04-12",
      "sum_amount": "716242.10",
      "tx_count": "280",
      "sum_principal": "133279.25",
      "sum_interest": "168305.75",
      "sum_fee": "10351.00",
      "sum_penalty": "5200.00",
      "sum_overpaid": "11399.00",
      "sum_close": "311252.80",
      "sum_bad_debt": "0.00"
    },
    {
      "paid_date": "2026-04-13",
      "sum_amount": "386807.00",
      "tx_count": "146",
      "sum_principal": "76950.00",
      "sum_interest": "90832.00",
      "sum_fee": "5664.00",
      "sum_penalty": "2793.00",
      "sum_overpaid": "4069.00",
      "sum_close": "173446.00",
      "sum_bad_debt": "0.00"
    },
    {
      "paid_date": "2026-04-14",
      "sum_amount": "366194.00",
      "tx_count": "149",
      "sum_principal": "80929.00",
      "sum_interest": "94634.00",
      "sum_fee": "6702.00",
      "sum_penalty": "2748.00",
      "sum_overpaid": "1041.00",
      "sum_close": "182265.00",
      "sum_bad_debt": "0.00"
    },
    {
      "paid_date": "2026-04-15",
      "sum_amount": "910979.00",
      "tx_count": "354",
      "sum_principal": "199765.00",
      "sum_interest": "255233.00",
      "sum_fee": "16147.00",
      "sum_penalty": "6986.00",
      "sum_overpaid": "462.00",
      "sum_close": "471145.00",
      "sum_bad_debt": "0.00"
    },
    {
      "paid_date": "2026-04-16",
      "sum_amount": "1563666.98",
      "tx_count": "630",
      "sum_principal": "182653.00",
      "sum_interest": "237803.00",
      "sum_fee": "15124.00",
      "sum_penalty": "8000.00",
      "sum_overpaid": "748.00",
      "sum_close": "434525.60",
      "sum_bad_debt": "0.00"
    },
    {
      "paid_date": "2026-04-17",
      "sum_amount": "712142.40",
      "tx_count": "315",
      "sum_principal": "158132.00",
      "sum_interest": "204962.00",
      "sum_fee": "13421.00",
      "sum_penalty": "8506.00",
      "sum_overpaid": "783.00",
      "sum_close": "373201.20",
      "sum_bad_debt": "0.00"
    },
    {
      "paid_date": "2026-04-18",
      "sum_amount": "593171.40",
      "tx_count": "241",
      "sum_principal": "121084.00",
      "sum_interest": "153928.00",
      "sum_fee": "9679.00",
      "sum_penalty": "3149.00",
      "sum_overpaid": "2269.00",
      "sum_close": "284010.20",
      "sum_bad_debt": "0.00"
    },
    {
      "paid_date": "2026-04-19",
      "sum_amount": "413441.68",
      "tx_count": "179",
      "sum_principal": "78696.00",
      "sum_interest": "103016.00",
      "sum_fee": "6550.00",
      "sum_penalty": "6524.00",
      "sum_overpaid": "2704.00",
      "sum_close": "188262.00",
      "sum_bad_debt": "0.00"
    },
    {
      "paid_date": "2026-04-20",
      "sum_amount": "1382194.60",
      "tx_count": "548",
      "sum_principal": "305142.00",
      "sum_interest": "402214.00",
      "sum_fee": "24781.00",
      "sum_penalty": "13128.00",
      "sum_overpaid": "298.00",
      "sum_close": "731356.80",
      "sum_bad_debt": "0.00"
    },
    {
      "paid_date": "2026-04-21",
      "sum_amount": "913136.80",
      "tx_count": "382",
      "sum_principal": "158410.00",
      "sum_interest": "185608.00",
      "sum_fee": "12777.00",
      "sum_penalty": "7872.00",
      "sum_overpaid": "7430.00",
      "sum_close": "355757.40",
      "sum_bad_debt": "0.00"
    },
    {
      "paid_date": "2026-04-22",
      "sum_amount": "696415.75",
      "tx_count": "286",
      "sum_principal": "117698.00",
      "sum_interest": "143171.00",
      "sum_fee": "8800.00",
      "sum_penalty": "14686.75",
      "sum_overpaid": "250.00",
      "sum_close": "267207.00",
      "sum_bad_debt": "0.00"
    },
    {
      "paid_date": "2026-04-23",
      "sum_amount": "734414.62",
      "tx_count": "298",
      "sum_principal": "121835.00",
      "sum_interest": "146922.75",
      "sum_fee": "9334.00",
      "sum_penalty": "6614.00",
      "sum_overpaid": "8305.00",
      "sum_close": "278091.75",
      "sum_bad_debt": "0.00"
    },
    {
      "paid_date": "2026-04-24",
      "sum_amount": "914812.40",
      "tx_count": "362",
      "sum_principal": "209382.00",
      "sum_interest": "243845.50",
      "sum_fee": "15954.00",
      "sum_penalty": "5467.50",
      "sum_overpaid": "3418.00",
      "sum_close": "466236.70",
      "sum_bad_debt": "0.00"
    },
    {
      "paid_date": "2026-04-25",
      "sum_amount": "683186.00",
      "tx_count": "276",
      "sum_principal": "280880.00",
      "sum_interest": "358099.00",
      "sum_fee": "22788.00",
      "sum_penalty": "14153.00",
      "sum_overpaid": "7266.00",
      "sum_close": "661767.00",
      "sum_bad_debt": "0.00"
    },
    {
      "paid_date": "2026-04-26",
      "sum_amount": "272447.00",
      "tx_count": "115",
      "sum_principal": "107916.00",
      "sum_interest": "148202.00",
      "sum_fee": "9016.00",
      "sum_penalty": "5875.00",
      "sum_overpaid": "438.00",
      "sum_close": "265134.00",
      "sum_bad_debt": "0.00"
    },
    {
      "paid_date": "2026-04-27",
      "sum_amount": "459175.00",
      "tx_count": "196",
      "sum_principal": "186366.00",
      "sum_interest": "241732.00",
      "sum_fee": "14610.00",
      "sum_penalty": "8482.00",
      "sum_overpaid": "7971.00",
      "sum_close": "441722.00",
      "sum_bad_debt": "0.00"
    },
    {
      "paid_date": "2026-04-28",
      "sum_amount": "461123.20",
      "tx_count": "200",
      "sum_principal": "199369.00",
      "sum_interest": "235544.00",
      "sum_fee": "16112.00",
      "sum_penalty": "9070.00",
      "sum_overpaid": "2298.00",
      "sum_close": "449755.20",
      "sum_bad_debt": "0.00"
    },
    {
      "paid_date": "2026-04-29",
      "sum_amount": "351586.00",
      "tx_count": "131",
      "sum_principal": "148944.00",
      "sum_interest": "180660.00",
      "sum_fee": "11601.00",
      "sum_penalty": "5775.00",
      "sum_overpaid": "6553.00",
      "sum_close": "339258.00",
      "sum_bad_debt": "0.00"
    },
    {
      "paid_date": "2026-04-30",
      "sum_amount": "1609251.00",
      "tx_count": "621",
      "sum_principal": "690607.00",
      "sum_interest": "832194.00",
      "sum_fee": "54753.00",
      "sum_penalty": "22316.00",
      "sum_overpaid": "10501.00",
      "sum_close": "1575584.00",
      "sum_bad_debt": "0.00"
    }
  ],
  "messages": [],
  "stdout": "paid_date\tsum_amount\ttx_count\tsum_principal\tsum_interest\tsum_fee\tsum_penalty\tsum_overpaid\tsum_close\tsum_bad_debt\n2026-04-01\t1667588.78\t636\t346120.95\t413689.94\t28085.00\t13540.00\t1270.00\t787212.89\t0.00\n2026-04-02\t1146813.63\t455\t210872.08\t264002.55\t17383.00\t4589.00\t12816.00\t492257.63\t0.00\n2026-04-03\t1249910.60\t411\t253146.75\t303189.01\t19092.00\t7019.00\t164061.24\t575011.56\t0.00\n2026-04-04\t844897.00\t331\t175633.25\t223059.75\t14103.00\t6372.00\t1395.00\t412796.00\t0.00\n2026-04-05\t1661913.00\t625\t360284.00\t445775.00\t29741.00\t10415.00\t8715.00\t835800.00\t0.00\n2026-04-06\t1321682.65\t419\t195670.00\t242089.84\t15443.00\t6150.00\t210574.16\t446141.84\t0.00\n2026-04-07\t741852.10\t310\t147170.00\t198090.00\t12223.00\t4450.50\t0.00\t355632.80\t0.00\n2026-04-08\t957966.00\t340\t189267.00\t251951.00\t15163.00\t6532.00\t68129.00\t456381.00\t0.00\n2026-04-09\t805934.34\t321\t175563.25\t237727.05\t14418.00\t8957.00\t2426.58\t427708.30\t0.00\n2026-04-10\t2250142.83\t851\t489209.58\t598746.91\t38016.00\t15852.88\t4305.63\t1124515.09\t0.00\n2026-04-11\t823933.04\t307\t153413.00\t194742.00\t12397.00\t4262.00\t2333.00\t360552.00\t0.00\n2026-04-12\t716242.10\t280\t133279.25\t168305.75\t10351.00\t5200.00\t11399.00\t311252.80\t0.00\n2026-04-13\t386807.00\t146\t76950.00\t90832.00\t5664.00\t2793.00\t4069.00\t173446.00\t0.00\n2026-04-14\t366194.00\t149\t80929.00\t94634.00\t6702.00\t2748.00\t1041.00\t182265.00\t0.00\n2026-04-15\t910979.00\t354\t199765.00\t255233.00\t16147.00\t6986.00\t462.00\t471145.00\t0.00\n2026-04-16\t1563666.98\t630\t182653.00\t237803.00\t15124.00\t8000.00\t748.00\t434525.60\t0.00\n2026-04-17\t712142.40\t315\t158132.00\t204962.00\t13421.00\t8506.00\t783.00\t373201.20\t0.00\n2026-04-18\t593171.40\t241\t121084.00\t153928.00\t9679.00\t3149.00\t2269.00\t284010.20\t0.00\n2026-04-19\t413441.68\t179\t78696.00\t103016.00\t6550.00\t6524.00\t2704.00\t188262.00\t0.00\n2026-04-20\t1382194.60\t548\t305142.00\t402214.00\t24781.00\t13128.00\t298.00\t731356.80\t0.00\n2026-04-21\t913136.80\t382\t158410.00\t185608.00\t12777.00\t7872.00\t7430.00\t355757.40\t0.00\n2026-04-22\t696415.75\t286\t117698.00\t143171.00\t8800.00\t14686.75\t250.00\t267207.00\t0.00\n2026-04-23\t734414.62\t298\t121835.00\t146922.75\t9334.00\t6614.00\t8305.00\t278091.75\t0.00\n2026-04-24\t914812.40\t362\t209382.00\t243845.50\t15954.00\t5467.50\t3418.00\t466236.70\t0.00\n2026-04-25\t683186.00\t276\t280880.00\t358099.00\t22788.00\t14153.00\t7266.00\t661767.00\t0.00\n2026-04-26\t272447.00\t115\t107916.00\t148202.00\t9016.00\t5875.00\t438.00\t265134.00\t0.00\n2026-04-27\t459175.00\t196\t186366.00\t241732.00\t14610.00\t8482.00\t7971.00\t441722.00\t0.00\n2026-04-28\t461123.20\t200\t199369.00\t235544.00\t16112.00\t9070.00\t2298.00\t449755.20\t0.00\n2026-04-29\t351586.00\t131\t148944.00\t180660.00\t11601.00\t5775.00\t6553.00\t339258.00\t0.00\n2026-04-30\t1609251.00\t621\t690607.00\t832194.00\t54753.00\t22316.00\t10501.00\t1575584.00\t0.00\n",
  "stderr": "",
  "execution_time_ms": 1990
}